rsync_tasks/__init__.py
rsync_tasks/__main__.py
rsync_tasks/rsync_tasks.py
rsync_tasks/version.py
rsync_tasks/exceptions/__init__.py
rsync_tasks/log/__init__.py
rsync_tasks/resources/config.schema.yaml
rsync_tasks-0.1.5.dist-info/LICENSE
rsync_tasks-0.1.5.dist-info/METADATA
rsync_tasks-0.1.5.dist-info/WHEEL
rsync_tasks-0.1.5.dist-info/entry_points.txt
rsync_tasks-0.1.5.dist-info/top_level.txt
rsync_tasks-0.1.5.dist-info/RECORD
